simplepidcontroller/__init__.py
simplepidcontroller/controller.py
simplepidcontroller-1.0.0.dist-info/METADATA
simplepidcontroller-1.0.0.dist-info/WHEEL
simplepidcontroller-1.0.0.dist-info/licenses/LICENSE
simplepidcontroller-1.0.0.dist-info/RECORD
