Metadata-Version: 2.4
Name: simplepidcontroller
Version: 1.0.0
Summary: A simple PID controller in Python
Project-URL: homepage, https://github.com/anaphan1/pidcontroller/
Project-URL: issues, https://github.com/anaphan1/pidcontroller/issues
License-File: LICENSE
Classifier: License :: OSI Approved :: MIT License
Classifier: Operating System :: OS Independent
Classifier: Programming Language :: Python :: 3
Requires-Python: >=2.7
